fedora_image_uploader_messages/__init__.py
fedora_image_uploader_messages/publish.py
fedora_image_uploader_messages-1.2.0.dist-info/METADATA
fedora_image_uploader_messages-1.2.0.dist-info/WHEEL
fedora_image_uploader_messages-1.2.0.dist-info/entry_points.txt
fedora_image_uploader_messages-1.2.0.dist-info/licenses/LICENSE
fedora_image_uploader_messages-1.2.0.dist-info/RECORD
